sgwr/__init__.py
sgwr/alpha.py
sgwr/diagnostics.py
sgwr/sgwr.py
sgwr/summary.py
sgwr/fastsgwr/FastSGWR.py
sgwr/fastsgwr/__init__.py
sgwr/fastsgwr/__main__.py
sgwr/fastsgwr/diagnostics.py
sgwr/fastsgwr/sgwr_mpi.py
sgwr-0.4.dist-info/LICENSE.txt
sgwr-0.4.dist-info/METADATA
sgwr-0.4.dist-info/WHEEL
sgwr-0.4.dist-info/entry_points.txt
sgwr-0.4.dist-info/top_level.txt
sgwr-0.4.dist-info/RECORD
