Metadata-Version: 2.1
Name: sgwr
Version: 0.4
Summary: Python implementation of SGWR and Fast SGWR (MPI-enhanced)
Home-page: https://github.com/Lessani252/FastSGWR
Author: M. Naser Lessani (GIBD)
Author-email: naserlessani252@gmail.com
License: MIT
Requires-Python: >=3.7
License-File: LICENSE.txt
Requires-Dist: numpy
Requires-Dist: pandas
Requires-Dist: scikit-learn
Requires-Dist: click
Requires-Dist: mpi4py
Requires-Dist: scipy
Requires-Dist: spglm
Requires-Dist: matplotlib
